comorbidipy/__init__.py
comorbidipy/cli.py
comorbidipy/py.typed
comorbidipy/calculators/__init__.py
comorbidipy/calculators/comorbidity.py
comorbidipy/calculators/hfrs.py
comorbidipy/calculators/learning_disability.py
comorbidipy/codemaps/__init__.py
comorbidipy/codemaps/mapping.py
comorbidipy/codemaps/weights.py
comorbidipy-0.8.0.dist-info/METADATA
comorbidipy-0.8.0.dist-info/WHEEL
comorbidipy-0.8.0.dist-info/entry_points.txt
comorbidipy-0.8.0.dist-info/licenses/AUTHORS.md
comorbidipy-0.8.0.dist-info/licenses/LICENSE
comorbidipy-0.8.0.dist-info/RECORD
