Metadata-Version: 2.4
Name: comorbidipy
Version: 0.8.0
Summary: Python package to calculate comorbidity scores and other clinical risk scores.
Project-URL: Homepage, https://github.com/vvcb/comorbidipy
Project-URL: Repository, https://github.com/vvcb/comorbidipy
Project-URL: Issues, https://github.com/vvcb/comorbidipy/issues
Project-URL: Documentation, https://vvcb.github.io/comorbidipy
Author: vvcb
License: MIT License
License-File: AUTHORS.md
License-File: LICENSE
Keywords: clinical risk scores,comorbidity,data analysis,healthcare
Classifier: Development Status :: 4 - Beta
Classifier: Intended Audience :: Developers
Classifier: Intended Audience :: Healthcare Industry
Classifier: Intended Audience :: Science/Research
Classifier: License :: OSI Approved :: MIT License
Classifier: Natural Language :: English
Classifier: Programming Language :: Python :: 3.13
Classifier: Programming Language :: Python :: 3.14
Requires-Python: >=3.13
Requires-Dist: polars>=1.27.1
Requires-Dist: rich>=13.0.0
Requires-Dist: typer>=0.15.2
